LICENSE
MANIFEST.in
README.rst
setup.py
ideskeleton/__init__.py
ideskeleton/__main__.py
ideskeleton/builder.py
ideskeleton/ideprocesses.py
ideskeleton.egg-info/PKG-INFO
ideskeleton.egg-info/SOURCES.txt
ideskeleton.egg-info/dependency_links.txt
ideskeleton.egg-info/top_level.txt
tests/__init__.py
tests/__init__.pyc
tests/test_builder.py
tests/test_ideprocesses.py
tests/test_ideskeleton.pyc
tests/tests.pyproj
tests/.cache/v/cache/lastfailed
tests/__pycache__/test_builder.cpython-27-PYTEST.pyc
tests/__pycache__/test_ideprocesses.cpython-27-PYTEST.pyc
tests/__pycache__/test_ideskeleton.cpython-27-PYTEST.pyc
tests/data/ideskeleton_pyproj.xml
tests/data/ideskeleton_sln.txt
tests/data/tests_pyproj.xml