Metadata-Version: 1.1
Name: ideskeleton
Version: 0.13
Summary: Scaffolding of IDE project files such as Visual Studio from Python existingfolder structure
Home-page: http://github.com/jruizaranguren/ideskeleton
Author: Javier Ruiz Aranguren
Author-email: UNKNOWN
License: MIT
Platform: UNKNOWN
Classifier: Development Status :: 4 - Beta
Classifier: Environment :: Console
Classifier: Intended Audience :: Developers
Classifier: License :: OSI Approved :: MIT License
Classifier: Programming Language :: Python
Classifier: Programming Language :: Python :: 2.7
Classifier: Programming Language :: Python :: 3.3
Classifier: Programming Language :: Python :: 3.4
Classifier: Programming Language :: Python :: 3.5
Classifier: Topic :: Text Editors :: Integrated Development Environments (IDE)
